[{"url":"http://akas.imdb.com/title/tt0434409/?ref_=fn_ft_tt_1","id":"148","title":"V wie Vendetta (2005)","year":"2005","genreList":["Action","Drama","Thriller"],"countryList":["USA","UK","Germany"],"languageList":["English"],"keywordList":["dystopia","government","terrorist","freedom","revolution"],"description":"Tells the story of Evey Hammond and her unlikely but instrumental part in bringing down the fascist government that has taken control of a futuristic Great Britain. Saved from a life-and-death situation by a man in a Guy Fawkes mask who calls himself V, she learns a general summary of V's past and, after a time, decides to help him bring down those who committed the atrocities that led to Britain being in the shape that it is in. Written by ameelmore","budget":"$54,000,000","gross":"$70,496,802","ratingValue":"8.2","ratingCount":"809,093","duration":"2h 12min","aspectRatio":"2.35 : 1","contentRating":"16","reviews":"2,054 user","critics":"523 critic","castList":["Natalie Portman","Hugo Weaving","Stephen Rea","Stephen Fry","John Hurt","Tim Pigott-Smith","Rupert Graves","Roger Allam","Ben Miles","Sinéad Cusack","Natasha Wightman","John Standing","Eddie Marsan","Clive Ashborn","Emma Field-Rayner"],"characterList":["Evey","V","Finch","Deitrich","Adam Sutler","Creedy","Dominic","Lewis Prothero","Dascomb","Delia Surridge","Valerie","Lilliman","Etheridge","Guy Fawkes","Guy Fawkes Lover (as Emma Field Rayner)"],"directorList":["James McTeigue"]}]