[{"url":"http://akas.imdb.com/title/tt0047478/?ref_=fn_ft_tt_1","id":"19","title":"Die sieben Samurai (1954)","year":"1954","genreList":["Action","Adventure","Drama"],"countryList":["Japan"],"languageList":["Japanese"],"keywordList":["samurai","battle","japan","16th century","practice"],"description":"A veteran samurai, who has fallen on hard times, answers a village's request for protection from bandits. He gathers 6 other samurai to help him, and they teach the townspeople how to defend themselves, and they supply the samurai with three small meals a day. The film culminates in a giant battle when 40 bandits attack the village. Written by Colin Tinto &lt;cst@imdb.com&gt;","budget":"$2,000,000","gross":"$269,061","ratingValue":"8.7","ratingCount":"233,826","duration":"3h 27min","aspectRatio":"1.37 : 1","contentRating":"16","reviews":"601 user","critics":"155 critic","castList":["Toshirô Mifune","Takashi Shimura","Keiko Tsushima","Yukiko Shimazaki","Kamatari Fujiwara","Daisuke Katô","Isao Kimura","Minoru Chiaki","Seiji Miyaguchi","Yoshio Kosugi","Bokuzen Hidari","Yoshio Inaba","Yoshio Tsuchiya","Kokuten Kôdô","Eijirô Tôno"],"characterList":["Kikuchiyo (as Toshiro Mifune)","Kambei Shimada","Shino","Wife (as Yukio Shimazaki)","Farmer Manzo","Shichiroji (as Daisake Kato)","Katsushiro (as Ko Kimura)","Heihachi","Kyuzo","Farmer Mosuke","Farmer Yohei","Gorobei Katayama","Farmer Rikichi","Old Man Gisaku (as Kuninori Todo)","Thief (as Eijiro Tono)"],"directorList":["Akira Kurosawa"]}]