[{"url":"http://akas.imdb.com/title/tt1216275/?ref_=fn_ft_tt_1","id":"380","title":"13 Semester (2009)","year":"2009","genreList":["Comedy","Drama","Romance"],"countryList":["Germany"],"languageList":["German"],"keywordList":["urination","sitting on a toilet","cook","kitchen","part time job"],"description":"The friends Moritz and Dirk get accepted at the TU Darmstadt and leave their small home village in Brandenburg to set out for the big town to study business arithmetic (mathematical economics).","budget":"","gross":"","ratingValue":"6.8","ratingCount":"1,608","duration":"1h 41min","aspectRatio":"","contentRating":"0","reviews":"1 user","critics":"14 critic","castList":["Max Riemelt","Dieter Mann","Robert Gwisdek","Amit Shah","Moritz Pliquet","Daniel Zillmann","Cyril Sjöström","Alex Holike","Benjamin Kramme","Michael Herl","Alexander Fehling","James Meuser","Maria Vogt","Claudia Eisinger","Ole Micha Spörkel"],"characterList":["Momo","Professor Schäfer","Dirk","Aswin","Arne","Käthe","Flo","Jugendherbergsgast","Uwe (as Benjamin Felix Kramme)","Hennes","Bernd","Jacques","Bibbi","Kerstin","Hans"],"directorList":["Frieder Wittich"]}]