[{"url":"http://akas.imdb.com/title/tt2404519/?ref_=fn_ft_tt_1","id":"563","title":"3G - A Killer Connection (2013)","year":"2013","genreList":["Horror","Sci-Fi","Thriller"],"countryList":["India"],"languageList":["English","Hindi"],"keywordList":["mobile phone","murder","knife","cult","ghost"],"description":"Sam purchase's a second hand cellphone and starts getting mysterious calls.","budget":"","gross":"","ratingValue":"3.6","ratingCount":"931","duration":"2h 5min","aspectRatio":"2.35 : 1","contentRating":"","reviews":"12 user","critics":"9 critic","castList":["Neil Nitin Mukesh","Sonal Chauhan","Himani Chauhan","Shantanu Ray Chhibber","Devraj Das","Asheesh Kapur","Amol Lal","Vishaarad Sharan","Mrinalini Sharma","Konrad Thorpe"],"characterList":["Sam","Sheena","","the Evil Priest","Brandy","Mong Hayward","Professor","Jaden","Chaima / Jasmine",""],"directorList":["Sheershak Anand","Shantanu Ray Chhibber"]}]