[{"url":"http://akas.imdb.com/title/tt0061523/?ref_=fn_ft_tt_1","id":"787","title":"Die Gräfin von Hongkong (1967)","year":"1967","genreList":["Comedy","Romance"],"countryList":["UK"],"languageList":["English","French"],"keywordList":["hong kong","ocean liner","countess","russian","luxury liner"],"description":"In Hong Kong, the wealthy Ogden Mears is traveling in a transatlantic and is near to be assigned Saudi Arabia Ambassador and is divorcing from his wife Martha. His friend Harvey and he are invited by their old friend Clark to go to a nightclub with three aristocratic Russian refugees on their last night. Ogden drinks too much and spends the night with Countess Natascha. On the next morning, while sailing back home, Ogdeb finds Natascha hidden in his cabin wearing a ball gown and with no documents. The stowaway explains that she wants to go to the United States and Ogden is worried with his career. But Harvey convinces him to help Natascha. Ogden falls in love with Natascha and together with Harvey, they plot a fake marriage of Natascha with his valet Hudson. But things get complicated when immigration requests her documents and Martha arrives on board. Written by Claudio Carvalho, Rio de Janeiro, Brazil","budget":"$3,500,000","gross":"","ratingValue":"6.1","ratingCount":"3,904","duration":"2h","aspectRatio":"1.85 : 1","contentRating":"","reviews":"47 user","critics":"18 critic","castList":["Marlon Brando","Sophia Loren","Sydney Chaplin","Tippi Hedren","Patrick Cargill","Michael Medwin","Oliver Johnston","John Paul","Angela Scoular","Margaret Rutherford","Peter Bartlett","Bill Nagy","Dilys Laye","Angela Pringle","Jenny Bridges"],"characterList":["Ogden Mears","Natascha","Harvey Crothers","Martha Mears","Henry L. Arthur Hudson","John Felix","Milton Clark","The Captain","The Society Girl","Miss Gaulswallow","Steward","Crawford","Saleswoman","Baroness","Countess"],"directorList":["Charles Chaplin"]}]