[
  {
    "gross":"$201,573,391",
    "year":"1998",
    "castList":[
      "Bruce Willis",
      "Billy Bob Thornton",
      "Ben Affleck",
      "Liv Tyler",
      "Will Patton",
      "Steve Buscemi",
      "William Fichtner",
      "Owen Wilson",
      "Michael Clarke Duncan",
      "Peter Stormare",
      "Ken Hudson Campbell",
      "Jessica Steen",
      "Keith David",
      "Chris Ellis",
      "Jason Isaacs"
    ],
    "genreList":[
      "Action",
      "Adventure",
      "Sci-Fi",
      "Thriller"
    ],
    "description":"It is just another day at the National Aeronautics and Space Administration (NASA), a few astronauts were repairing a satellite until, out of nowhere, a series of asteroids came crashing into the shuttle, destroying it. These asteroids also decimated New York soon thereafter. Then, NASA discovered that there is an asteroid roughly the size of Texas heading towards the Earth, and when it does hit the Earth, the planet itself and all of its inhabitants will be obliterated, worse, the asteroid will hit the Earth in 18 days. Unfortunately, NASA's plans to destroy the asteroid are irrelevant. That is when the U.S. military decides to use a nuclear warhead to blow the asteroid to pieces. Then, scientists decide to blow the asteroid with the warhead inside the asteroid itself. The only man to do it, is an oil driller named Harry Stamper and his group of misfit drillers and geologists. As he and his drill team prepare for space excavation, the asteroid is still heading towards the Earth. When...",
    "directorList":[
      "Michael Bay"
    ],
    "characterList":[
      "Harry S. Stamper",
      "Dan Truman",
      "A.J. Frost",
      "Grace Stamper",
      "Chick",
      "Rockhound",
      "Colonel Willie Sharp",
      "Oscar",
      "Bear",
      "Lev Andropov",
      "Max",
      "Co-Pilot Jennifer Watts",
      "General Kimsey",
      "Flight Director Clark",
      "Ronald Quincy"
    ],
    "title":"Armageddon",
    "ratingCount":"327,258",
    "countryList":[
      "USA"
    ],
    "url":"http://akas.imdb.com/title/tt0120591/?ref_=fn_ft_tt_1",
    "duration":"2h 31min",
    "ratingValue":"6.6",
    "budget":"$140,000,000"
  }
]
