[
  {
    "gross":"$305,388,685",
    "year":"2003",
    "castList":[
      "Johnny Depp",
      "Geoffrey Rush",
      "Orlando Bloom",
      "Keira Knightley",
      "Jack Davenport",
      "Jonathan Pryce",
      "Lee Arenberg",
      "Mackenzie Crook",
      "Damian O'Hare",
      "Giles New",
      "Angus Barnett",
      "David Bailie",
      "Michael Berry Jr.",
      "Isaac C. Singleton Jr.",
      "Kevin McNally"
    ],
    "genreList":[
      "Action",
      "Adventure",
      "Fantasy"
    ],
    "description":"This swash-buckling tale follows the quest of Captain Jack Sparrow, a savvy pirate, and Will Turner, a resourceful blacksmith, as they search for Elizabeth Swann. Elizabeth, the daughter of the governor and the love of Will's life, has been kidnapped by the feared Captain Barbossa. Little do they know, but the fierce and clever Barbossa has been cursed. He, along with his large crew, are under an ancient curse, doomed for eternity to neither live, nor die. That is, unless a blood sacrifice is made.",
    "directorList":[
      "Gore Verbinski"
    ],
    "characterList":[
      "Jack Sparrow",
      "Barbossa",
      "Will Turner",
      "Elizabeth Swann",
      "Norrington",
      "Governor Weatherby Swann",
      "Pintel",
      "Ragetti",
      "Lt. Gillette",
      "Murtogg",
      "Mullroy",
      "Cotton",
      "Twigg",
      "Bo'sun",
      "Joshamee Gibbs"
    ],
    "title":"Pirates of the Caribbean: The Curse of the Black Pearl",
    "ratingCount":"824,839",
    "countryList":[
      "USA"
    ],
    "url":"http://akas.imdb.com/title/tt0325980/?ref_=fn_ft_tt_1",
    "duration":"2h 23min",
    "ratingValue":"8.1",
    "budget":"$140,000,000"
  }
]
