[
  {
    "gross":"$102,608,827",
    "year":"2004",
    "castList":[
      "Leonardo DiCaprio",
      "Cate Blanchett",
      "Kate Beckinsale",
      "John C. Reilly",
      "Alec Baldwin",
      "Alan Alda",
      "Ian Holm",
      "Danny Huston",
      "Gwen Stefani",
      "Jude Law",
      "Adam Scott",
      "Matt Ross",
      "Kelli Garner",
      "Frances Conroy",
      "Brent Spiner"
    ],
    "genreList":[
      "Biography",
      "Drama",
      "History"
    ],
    "description":"Biopic of billionaire",
    "directorList":[
      "Martin Scorsese"
    ],
    "characterList":[
      "Howard Hughes",
      "Katharine Hepburn",
      "Ava Gardner",
      "Noah Dietrich",
      "Juan Trippe",
      "Senator Ralph Owen Brewster",
      "Professor Fitz",
      "Jack Frye",
      "Jean Harlow",
      "Errol Flynn",
      "Johnny Meyer",
      "Glenn Odekirk",
      "Faith Domergue",
      "Mrs. Hepburn",
      "Robert Gross"
    ],
    "title":"The Aviator",
    "ratingCount":"268,845",
    "countryList":[
      "USA",
      "Germany"
    ],
    "url":"http://akas.imdb.com/title/tt0338751/?ref_=fn_ft_tt_1",
    "duration":"2h 50min",
    "ratingValue":"7.5",
    "budget":"$110,000,000"
  }
]
