[
  {
    "gross":"$58,220,776",
    "year":"1999",
    "castList":[
      "Robin Williams",
      "Embeth Davidtz",
      "Sam Neill",
      "Oliver Platt",
      "Kiersten Warren",
      "Wendy Crewson",
      "Hallie Kate Eisenberg",
      "Lindze Letherman",
      "Angela Landis",
      "John Michael Higgins",
      "Bradley Whitford",
      "Igor Hiller",
      "Joe Bellan",
      "Brett Wagner",
      "Stephen Root"
    ],
    "genreList":[
      "Comedy",
      "Drama",
      "Sci-Fi"
    ],
    "description":"This film follows the 'life' and times of the lead character, an android who is purchased as a household robot programmed to perform menial tasks. Within a few days the Martin family realizes that they don't have an ordinary droid as Andrew begins to experience emotions and creative thought. In a story that spans two centuries, Andrew learns the intricacies of humanity while trying to stop those who created him from destroying him.",
    "directorList":[
      "Chris Columbus"
    ],
    "characterList":[
      "Andrew Martin",
      "Little Miss Amanda Martin",
      "Portia Charney",
      "'Sir' Richard Martin",
      "Rupert Burns",
      "Galatea",
      "'Ma'am' Martin",
      "Little Miss Amanda Martin - Age 7",
      "'Miss' Grace Martin - Age 9",
      "'Miss' Grace Martin",
      "Bill Feingold - Martin's Lawyer",
      "Lloyd Charney",
      "Lloyd Charney - Age 10"
    ],
    "title":"Bicentennial Man",
    "ratingCount":"89,439",
    "countryList":[
      "USA",
      "Germany"
    ],
    "url":"http://akas.imdb.com/title/tt0182789/?ref_=fn_ft_tt_1",
    "duration":"2h 12min",
    "ratingValue":"6.8",
    "budget":"$100,000,000"
  }
]
