[
  {
    "gross":"$51,396,781",
    "year":"2001",
    "castList":[
      "Jude Law",
      "Ed Harris",
      "Rachel Weisz",
      "Joseph Fiennes",
      "Bob Hoskins",
      "Ron Perlman",
      "Eva Mattes",
      "Gabriel Thomson",
      "Matthias Habich",
      "Sophie Rois",
      "Ivan Shvedoff",
      "Mario Bandi",
      "Hans Martin Stier",
      "Clemens Schick",
      "Mikhail Matveev"
    ],
    "genreList":[
      "Drama",
      "History",
      "War"
    ],
    "description":"In World War II, the fall of Stalingrad will mean the collapse of the whole country. The Germans and Russians are fighting over every block, leaving only ruins behind. The Russian sniper Vassili Zaitsev stalks the Germans, taking them out one by one, thus hurting the morale of the German troops. The political officer Danilov leads him on, publishing his efforts to give his countrymen some hope. But Vassili eventually start to feel that he can not live up to the expectations on him. He and Danilov fall in love with the same girl, Tanya, a female soldier. From Germany comes the master sniper König to put an end to the extraordinary skilled Russian sniper.",
    "directorList":[
      "Jean-Jacques Annaud"
    ],
    "characterList":[
      "Vassili",
      "Major König",
      "Tania Chernova",
      "Commisar Danilov",
      "Nikita Khrushchev",
      "Koulikov",
      "Mother Filipov",
      "Sacha Filipov",
      "General Paulus",
      "Ludmilla",
      "Volodya",
      "Anton",
      "Red Army General",
      "German NCO",
      "Grandfather"
    ],
    "title":"Enemy at the Gates",
    "ratingCount":"192,370",
    "countryList":[
      "USA",
      "France",
      "Germany",
      "UK",
      "Ireland"
    ],
    "url":"http://akas.imdb.com/title/tt0215750/?ref_=fn_ft_tt_1",
    "duration":"2h 11min",
    "ratingValue":"7.6",
    "budget":"$68,000,000"
  }
]
